mail2news.py
news2mail.py
whitelist.py
wlp.py
wlp_parser.py
pygn-0.12.0.dist-info/COPYING
pygn-0.12.0.dist-info/METADATA
pygn-0.12.0.dist-info/WHEEL
pygn-0.12.0.dist-info/entry_points.txt
pygn-0.12.0.dist-info/top_level.txt
pygn-0.12.0.dist-info/RECORD
