Metadata-Version: 2.1
Name: pygn
Version: 0.12.0
Summary: The Python Gateway Script: news2mail mail2news gateway
Author-email: Cosimo Alfarano <kalfa@debian.org>, Matěj Cepl <mcepl@cepl.eu>
License: GPL-3.0
Project-URL: Homepage, https://sr.ht/~mcepl/pyg
Project-URL: Communication, https://lists.sr.ht/~mcepl/devel
Keywords: nntp,email,gateway
Classifier: Programming Language :: Python :: 3
Classifier: Development Status :: 3 - Alpha
Classifier: Intended Audience :: System Administrators
Classifier: Topic :: Utilities
Classifier: Topic :: Communications :: Usenet News
Classifier: Environment :: Console
Classifier: Operating System :: OS Independent
Classifier: License :: OSI Approved :: GNU General Public License v3 (GPLv3)
Requires-Python: >=3.6
License-File: COPYING
Requires-Dist: rply
Requires-Dist: pynntp; python_version >= "3.12"
